LICENSE
premiscale/__init__.py
premiscale/api/__init__.py
premiscale/api/healthcheck/__init__.py
premiscale/api/healthcheck/routes.py
premiscale/api/metrics/__init__.py
premiscale/api/metrics/routes.py
premiscale/autoscaling/__init__.py
premiscale/autoscaling/actions.py
premiscale/autoscaling/group.py
premiscale/cli.py
premiscale/config/__init__.py
premiscale/config/default.yaml
premiscale/config/parse.py
premiscale/config/schemas/__init__.py
premiscale/config/schemas/schema.v1alpha1.yaml
premiscale/config/v1alpha1.py
premiscale/daemon.py
premiscale/errors.py
premiscale/hypervisor/__init__.py
premiscale/hypervisor/_base.py
premiscale/hypervisor/esx.py
premiscale/hypervisor/esx_data.py
premiscale/hypervisor/qemu.py
premiscale/hypervisor/qemu_data.py
premiscale/metrics/__init__.py
premiscale/metrics/state/__init__.py
premiscale/metrics/state/_base.py
premiscale/metrics/state/local.py
premiscale/metrics/state/mysql.py
premiscale/metrics/state/sql/__init__.py
premiscale/metrics/state/sql/create_asg.sql
premiscale/metrics/state/sql/initialize_database.sql
premiscale/metrics/timeseries/__init__.py
premiscale/metrics/timeseries/_base.py
premiscale/metrics/timeseries/influxdb.py
premiscale/metrics/timeseries/local.py
premiscale/platform/__init__.py
premiscale/platform/utils.py
premiscale/reconciliation/__init__.py
premiscale/reconciliation/internal.py
premiscale/reconciliation/kubernetes.py
premiscale/utils.py
premiscale-0.0.7.dist-info/LICENSE
premiscale-0.0.7.dist-info/METADATA
premiscale-0.0.7.dist-info/WHEEL
premiscale-0.0.7.dist-info/entry_points.txt
premiscale-0.0.7.dist-info/RECORD
