Metadata-Version: 2.1
Name: premiscale
Version: 0.0.7
Summary: A Kubernetes controller that automatically scales and administers private virtual and physical infrastructure
Home-page: https://premiscale.com
License: BSL 1.1
Keywords: premiscale,kubernetes,virtual machine,infrastructure,autoscaling,asg,qemu,xen,esx,esxi,kvm,libvirt
Author: Emma Doyle
Author-email: emma@premiscale.com
Maintainer: Emma Doyle
Maintainer-email: emma@premiscale.com
Requires-Python: >=3.10,<4.0
Classifier: Development Status :: 2 - Pre-Alpha
Classifier: Intended Audience :: Developers
Classifier: Intended Audience :: System Administrators
Classifier: License :: Other/Proprietary License
Classifier: Natural Language :: English
Classifier: Programming Language :: Python :: 3
Classifier: Programming Language :: Python :: 3.10
Classifier: Programming Language :: Python :: 3.11
Classifier: Programming Language :: Python :: 3.12
Classifier: Programming Language :: Python :: 3 :: Only
Classifier: Topic :: System :: Clustering
Classifier: Topic :: System :: Hardware
Classifier: Topic :: System :: Monitoring
Classifier: Topic :: System :: Systems Administration
Classifier: Topic :: Utilities
Requires-Dist: Flask (>=3.0.0,<4.0.0)
Requires-Dist: attrs (>=23.2.0,<24.0.0)
Requires-Dist: cachetools (>=5.3.3,<6.0.0)
Requires-Dist: cattrs (>=23.2.3,<24.0.0)
Requires-Dist: flask-cors (>=4.0,<5.0)
Requires-Dist: grpcio (>=1.64.1,<2.0.0)
Requires-Dist: influxdb-client[ciso] (>=1.44.0,<2.0.0)
Requires-Dist: libvirt-python (>=10,<11)
Requires-Dist: prometheus-client (>=0.20.0,<0.21.0)
Requires-Dist: pyhumps (>=3.8.0,<4.0.0)
Requires-Dist: requests (>=2.32.3,<3.0.0)
Requires-Dist: ruamel-yaml (>=0.18.6,<0.19.0)
Requires-Dist: setproctitle (>=1.3,<2.0)
Requires-Dist: sqlmodel (>=0,<1)
Requires-Dist: tinyflux (>=1.0.0,<2.0.0)
Requires-Dist: websockets (>=12.0,<13.0)
Requires-Dist: wrapt (>=1.16.0,<2.0.0)
Requires-Dist: xmltodict (>=0.13.0,<0.14.0)
Requires-Dist: yamale (>=5,<6)
Project-URL: Documentation, https://docs.premiscale.com
Project-URL: Repository, https://github.com/premiscale/premiscale
